langwatch/__init__.py
langwatch/key_manager.py
langwatch/providers.py
langwatch/rate_limiter.py
langwatch/alerts/__init__.py
langwatch/alerts/base.py
langwatch/alerts/email.py
langwatch/alerts/slack.py
langwatch/alerts/webhook.py
langwatch/langchain/__init__.py
langwatch/langchain/chat_with_fallback.py
langwatch/templates/__init__.py
langwatch/templates/email_templates.py
fika_langwatch-0.3.6.dist-info/METADATA
fika_langwatch-0.3.6.dist-info/WHEEL
fika_langwatch-0.3.6.dist-info/licenses/LICENSE
fika_langwatch-0.3.6.dist-info/RECORD
