Metadata-Version: 2.4
Name: fika-langwatch
Version: 0.3.6
Summary: LangChain wrapper with automatic fallback and alert notifications when API keys fail
Project-URL: Homepage, https://github.com/pupiltree/fika-langwatch
Project-URL: Documentation, https://github.com/pupiltree/fika-langwatch#readme
Project-URL: Repository, https://github.com/pupiltree/fika-langwatch
Project-URL: Issues, https://github.com/pupiltree/fika-langwatch/issues
Author: FIKA Private Limited
Author-email: Rahul Kumar <rahul@pupiltree.ai>, Nikhil Sukhte <nikhil@pupiltree.ai>
License: Copyright (c) 2026 FIKA Private Limited. All Rights Reserved.
License-File: LICENSE
Keywords: alerts,api-keys,fallback,langchain,llm,monitoring
Classifier: Development Status :: 4 - Beta
Classifier: Intended Audience :: Developers
Classifier: License :: Other/Proprietary License
Classifier: Programming Language :: Python :: 3
Classifier: Programming Language :: Python :: 3.9
Classifier: Programming Language :: Python :: 3.10
Classifier: Programming Language :: Python :: 3.11
Classifier: Programming Language :: Python :: 3.12
Classifier: Topic :: Software Development :: Libraries :: Python Modules
Requires-Python: >=3.9
Requires-Dist: aiosmtplib>=3.0.0
Requires-Dist: httpx>=0.25.0
Requires-Dist: langchain-anthropic>=0.1.0
Requires-Dist: langchain-core>=0.1.0
Requires-Dist: langchain-google-genai>=1.0.0
Requires-Dist: langchain-openai>=0.1.0
Provides-Extra: dev
Requires-Dist: pytest-asyncio>=0.21.0; extra == 'dev'
Requires-Dist: pytest>=7.0.0; extra == 'dev'
Requires-Dist: ruff>=0.1.0; extra == 'dev'
